build_scripts/installer-version.py
flora/__init__.py
flora/pyinstaller.spec
flora/clvm/singleton.py
flora/cmds/__init__.py
flora/cmds/configure.py
flora/cmds/farm.py
flora/cmds/farm_funcs.py
flora/cmds/flora.py
flora/cmds/init.py
flora/cmds/init_funcs.py
flora/cmds/keys.py
flora/cmds/keys_funcs.py
flora/cmds/netspace.py
flora/cmds/netspace_funcs.py
flora/cmds/plotnft.py
flora/cmds/plotnft_funcs.py
flora/cmds/plots.py
flora/cmds/show.py
flora/cmds/start.py
flora/cmds/start_funcs.py
flora/cmds/stop.py
flora/cmds/units.py
flora/cmds/wallet.py
flora/cmds/wallet_funcs.py
flora/consensus/__init__.py
flora/consensus/block_body_validation.py
flora/consensus/block_creation.py
flora/consensus/block_header_validation.py
flora/consensus/block_record.py
flora/consensus/block_rewards.py
flora/consensus/block_root_validation.py
flora/consensus/blockchain.py
flora/consensus/blockchain_interface.py
flora/consensus/coinbase.py
flora/consensus/condition_costs.py
flora/consensus/constants.py
flora/consensus/cost_calculator.py
flora/consensus/default_constants.py
flora/consensus/deficit.py
flora/consensus/difficulty_adjustment.py
flora/consensus/find_fork_point.py
flora/consensus/full_block_to_block_record.py
flora/consensus/get_block_challenge.py
flora/consensus/make_sub_epoch_summary.py
flora/consensus/multiprocess_validation.py
flora/consensus/network_type.py
flora/consensus/pos_quality.py
flora/consensus/pot_iterations.py
flora/consensus/vdf_info_computation.py
flora/daemon/__init__.py
flora/daemon/client.py
flora/daemon/server.py
flora/daemon/windows_signal.py
flora/farmer/__init__.py
flora/farmer/farmer.py
flora/farmer/farmer_api.py
flora/full_node/__init__.py
flora/full_node/block_store.py
flora/full_node/bundle_tools.py
flora/full_node/coin_store.py
flora/full_node/full_node.py
flora/full_node/full_node_api.py
flora/full_node/full_node_store.py
flora/full_node/generator.py
flora/full_node/mempool.py
flora/full_node/mempool_check_conditions.py
flora/full_node/mempool_manager.py
flora_blockchain-0.2.5.dist-info/LICENSE
flora_blockchain-0.2.5.dist-info/METADATA
flora_blockchain-0.2.5.dist-info/WHEEL
flora_blockchain-0.2.5.dist-info/entry_points.txt
flora_blockchain-0.2.5.dist-info/top_level.txt
flora_blockchain-0.2.5.dist-info/RECORD
